pyjmine/__init__.py
pyjmine/mappings.py
pyjmine/pyjmine.py
pyjmine-1.0.0.dist-info/METADATA
pyjmine-1.0.0.dist-info/WHEEL
pyjmine-1.0.0.dist-info/top_level.txt
pyjmine-1.0.0.dist-info/RECORD
