Metadata-Version: 2.1
Name: pyjmine
Version: 1.0.0
Summary: .
Home-page: https://t.me/maehdak_van
Author: Maehdakvan
Author-email: visitanimation@google.com
Project-URL: Bug Tracker, https://t.me/maehdak_van
Classifier: Programming Language :: Python :: 3
Classifier: License :: OSI Approved :: MIT License
Classifier: Operating System :: OS Independent
Requires-Python: >=3.6
Requires-Dist: jpype1
Requires-Dist: psutil
Requires-Dist: requests
Requires-Dist: lxml
